commonbwc/__init__.py
commonbwc/version.txt
commonbwc/views.py
commonbwc/views.py~
commonbwc/config/__init__.py
commonbwc/config/settings.py
commonbwc/config/settings.py~
commonbwc/lib/__init__.py
commonbwc/lib/forms.py
commonbwc/lib/forms.py~
commonbwc/lib/testing.py
commonbwc/lib/testing.py~
commonbwc/lib/views.py
commonbwc/lib/views.py~
commonbwc/templates/auth_error.html
commonbwc/templates/bad_request_error.html
commonbwc/templates/crud_addedit.html
commonbwc/templates/crud_manage.html
commonbwc/templates/crud_manage.js
commonbwc/templates/crud_manage_webgrid.html
commonbwc/templates/forbidden.html
commonbwc/templates/layout_testing.html
commonbwc/templates/not_found_error.html
commonbwc/templates/system_error.html
commonbwc/templates/user_messages.html
CommonBWC-0.2.2.dist-info/METADATA
CommonBWC-0.2.2.dist-info/WHEEL
CommonBWC-0.2.2.dist-info/top_level.txt
CommonBWC-0.2.2.dist-info/RECORD
