Metadata-Version: 2.1
Name: CommonBWC
Version: 0.2.2
Summary: A BlazeWeb component to hold libraries shared by other components and apps.
Home-page: https://github.com/blazelibs/commonbwc/
Author: Randy Syring
Author-email: randy.syring@level12.io
License: BSD
Platform: UNKNOWN
Classifier: Development Status :: 4 - Beta
Classifier: Intended Audience :: Developers
Classifier: License :: OSI Approved :: BSD License
Classifier: Operating System :: OS Independent
Classifier: Programming Language :: Python :: 2.7
Classifier: Programming Language :: Python :: 3.4
Classifier: Programming Language :: Python :: 3.5
Classifier: Topic :: Internet :: WWW/HTTP
Requires-Dist: BlazeForm (>=0.3.0)
Requires-Dist: BlazeWeb (>=0.3.0)
Provides-Extra: dev
Requires-Dist: codecov; extra == 'dev'
Requires-Dist: coverage; extra == 'dev'
Requires-Dist: flake8; extra == 'dev'
Requires-Dist: nose; extra == 'dev'
Requires-Dist: pyquery; extra == 'dev'
Requires-Dist: tox; extra == 'dev'
Requires-Dist: webtest; extra == 'dev'
Requires-Dist: wheel; extra == 'dev'
